ifgen/__init__.py
ifgen/__main__.py
ifgen/app.py
ifgen/dev_requirements.txt
ifgen/entry.py
ifgen/enums.py
ifgen/paths.py
ifgen/py.typed
ifgen/requirements.txt
ifgen/schemas.py
ifgen/commands/__init__.py
ifgen/commands/all.py
ifgen/commands/gen.py
ifgen/commands/svd.py
ifgen/common/__init__.py
ifgen/config/__init__.py
ifgen/config/svd.py
ifgen/data/default.yaml
ifgen/data/svd.yaml
ifgen/data/yambs.yaml
ifgen/data/plugins/struct_receiver.yaml
ifgen/data/schemas/BitField.yaml
ifgen/data/schemas/Config.yaml
ifgen/data/schemas/Enum.yaml
ifgen/data/schemas/Struct.yaml
ifgen/data/schemas/StructField.yaml
ifgen/data/schemas/StructFieldAlternate.yaml
ifgen/data/schemas/StructInstance.yaml
ifgen/data/schemas/SvdConfig.yaml
ifgen/data/schemas/SvdInstanceConfig.yaml
ifgen/data/schemas/has_bit_fields.yaml
ifgen/data/schemas/has_description.yaml
ifgen/data/schemas/has_expected_size.yaml
ifgen/data/schemas/has_json_indent.yaml
ifgen/data/schemas/has_namespace.yaml
ifgen/data/schemas/has_volatile.yaml
ifgen/data/svd/XMC4700.svd
ifgen/data/svd/mimxrt1176_cm4.svd
ifgen/data/svd/mimxrt1176_cm7.svd
ifgen/data/svd/rp2040.svd
ifgen/data/svd/rp2350.svd
ifgen/enum/__init__.py
ifgen/enum/common.py
ifgen/enum/header.py
ifgen/enum/map.py
ifgen/enum/source.py
ifgen/enum/test.py
ifgen/enum/python/__init__.py
ifgen/environment/__init__.py
ifgen/environment/field.py
ifgen/environment/padding.py
ifgen/generation/__init__.py
ifgen/generation/interface.py
ifgen/generation/json.py
ifgen/generation/test.py
ifgen/generation/python/__init__.py
ifgen/plugins/__init__.py
ifgen/plugins/struct_receiver/__init__.py
ifgen/struct/__init__.py
ifgen/struct/header.py
ifgen/struct/stream.py
ifgen/struct/test.py
ifgen/struct/util.py
ifgen/struct/methods/__init__.py
ifgen/struct/methods/bit.py
ifgen/struct/methods/common.py
ifgen/struct/methods/fields/__init__.py
ifgen/struct/methods/fields/common.py
ifgen/struct/methods/fields/getter.py
ifgen/struct/methods/fields/setter.py
ifgen/struct/python/__init__.py
ifgen-4.6.5.dist-info/licenses/LICENSE
ifgen-4.6.5.dist-info/METADATA
ifgen-4.6.5.dist-info/WHEEL
ifgen-4.6.5.dist-info/entry_points.txt
ifgen-4.6.5.dist-info/top_level.txt
ifgen-4.6.5.dist-info/RECORD
